CHANGES.txt
MANIFEST.in
README.md
setup.py
GeobricksGISRaster.egg-info/PKG-INFO
GeobricksGISRaster.egg-info/SOURCES.txt
GeobricksGISRaster.egg-info/dependency_links.txt
GeobricksGISRaster.egg-info/requires.txt
GeobricksGISRaster.egg-info/top_level.txt
geobricks_gis_raster/__init__.py
geobricks_gis_raster/__init__.pyc
geobricks_gis_raster/config/__init__.py
geobricks_gis_raster/config/__init__.pyc
geobricks_gis_raster/config/config.py
geobricks_gis_raster/config/config.pyc
geobricks_gis_raster/core/__init__.py
geobricks_gis_raster/core/__init__.pyc
geobricks_gis_raster/core/raster.py
geobricks_gis_raster/core/raster.pyc
geobricks_gis_raster/core/raster_mapalgebra.py
geobricks_gis_raster/core/raster_mapalgebra.pyc