Metadata-Version: 1.0
Name: GeobricksGISRaster
Version: 0.1.12
Summary: Geobricks library to process raster layers.
Home-page: http://pypi.python.org/pypi/GeobricksGISRaster/
Author: Simone Murzilli; Guido Barbaglia
Author-email: geobrickspy@gmail.com
License: LICENSE.txt
Keywords: geobricks,geoserver,gis,raster
Platform: UNKNOWN
